gen_material/assets/bg/ANEMO.png
gen_material/assets/bg/BG_MOB.png
gen_material/assets/bg/CRYO.png
gen_material/assets/bg/DENDRO.png
gen_material/assets/bg/ELECTRO.png
gen_material/assets/bg/GEO.png
gen_material/assets/bg/GYDRO.png
gen_material/assets/bg/MASKA_FARM_BOSS.png
gen_material/assets/bg/PYRO.png
gen_material/assets/font/Genshin_Impact.ttf
gen_material/assets/frame/ANEMO.png
gen_material/assets/frame/CRYO.png
gen_material/assets/frame/DENDRO.png
gen_material/assets/frame/ELECTRO.png
gen_material/assets/frame/FRAME_DAY_BOSS.png
gen_material/assets/frame/GEO.png
gen_material/assets/frame/GYDRO.png
gen_material/assets/frame/PYRO.png
gen_material/assets/LK_LOGO_X.png
gen_material/data/bossDB.py
gen_material/data/charterDB.py
gen_material/data/monsterDB.py
gen_material/material.py
gen_material/openfiles.py
gen_material-0.0.8.dist-info/WHEEL
gen_material-0.0.8.dist-info/METADATA
gen_material-0.0.8.dist-info/RECORD
